setup.py
django_generic_permissions/__init__.py
django_generic_permissions/backends.py
django_generic_permissions/base_models.py
django_generic_permissions/models.py
django_generic_permissions/mongoengine_models.py
django_generic_permissions/sql_models.py
django_generic_permissions/tests.py
django_generic_permissions/views.py
django_generic_permissions.egg-info/PKG-INFO
django_generic_permissions.egg-info/SOURCES.txt
django_generic_permissions.egg-info/dependency_links.txt
django_generic_permissions.egg-info/not-zip-safe
django_generic_permissions.egg-info/requires.txt
django_generic_permissions.egg-info/top_level.txt