Metadata-Version: 1.0
Name: django-generic-permissions
Version: 0.0.1
Summary: A generic permission framework for Django
Home-page: https://github.com/garrypolley/django_generic_permissions
Author: Garry Polley
Author-email: garrympolley@gmail.com
License: UNKNOWN
Platform: UNKNOWN
Classifier: Development Status :: 5 - Production/Stable
Classifier: Environment :: Web Environment
Classifier: Framework :: Django
Classifier: Intended Audience :: Developers
Classifier: Operating System :: OS Independent
Classifier: Programming Language :: Python
Classifier: Topic :: Utilities
